sedex/__init__.py
sedex/semebo.py
sedex-1.0.0.dist-info/LICENSE
sedex-1.0.0.dist-info/METADATA
sedex-1.0.0.dist-info/WHEEL
sedex-1.0.0.dist-info/top_level.txt
sedex-1.0.0.dist-info/RECORD
