Metadata-Version: 2.1
Name: sedex
Version: 1.0.0
Summary: SEDEX Messagebox Manager
Home-page: https://github.com/eraymann/sedex
Author: Elias Raymann
Author-email: elias.raymann@swisstopo.ch
License: UNKNOWN
Platform: UNKNOWN
Classifier: Development Status :: 5 - Production/Stable
Classifier: Programming Language :: Python :: 3.6
Classifier: License :: OSI Approved :: MIT License
Classifier: Operating System :: OS Independent
Requires-Python: >=2.7
